weppy_Assets-0.5.dist-info/DESCRIPTION.rst
weppy_Assets-0.5.dist-info/METADATA
weppy_Assets-0.5.dist-info/RECORD
weppy_Assets-0.5.dist-info/WHEEL
weppy_Assets-0.5.dist-info/metadata.json
weppy_Assets-0.5.dist-info/top_level.txt
weppy_assets/__init__.py
weppy_assets/ext.py
weppy_assets/webassets/__init__.py
weppy_assets/webassets/bundle.py
weppy_assets/webassets/cache.py
weppy_assets/webassets/env.py
weppy_assets/webassets/exceptions.py
weppy_assets/webassets/importlib.py
weppy_assets/webassets/loaders.py
weppy_assets/webassets/merge.py
weppy_assets/webassets/script.py
weppy_assets/webassets/six.py
weppy_assets/webassets/test.py
weppy_assets/webassets/updater.py
weppy_assets/webassets/utils.py
weppy_assets/webassets/version.py
weppy_assets/webassets/filter/__init__.py
weppy_assets/webassets/filter/autoprefixer.py
weppy_assets/webassets/filter/babel.py
weppy_assets/webassets/filter/cleancss.py
weppy_assets/webassets/filter/clevercss.py
weppy_assets/webassets/filter/closure.py
weppy_assets/webassets/filter/closure_stylesheets.py
weppy_assets/webassets/filter/closure_templates.py
weppy_assets/webassets/filter/coffee.py
weppy_assets/webassets/filter/compass.py
weppy_assets/webassets/filter/cssmin.py
weppy_assets/webassets/filter/cssprefixer.py
weppy_assets/webassets/filter/cssutils.py
weppy_assets/webassets/filter/datauri.py
weppy_assets/webassets/filter/dust.py
weppy_assets/webassets/filter/handlebars.py
weppy_assets/webassets/filter/jade.py
weppy_assets/webassets/filter/jinja2.py
weppy_assets/webassets/filter/jsmin.py
weppy_assets/webassets/filter/jst.py
weppy_assets/webassets/filter/less.py
weppy_assets/webassets/filter/less_ruby.py
weppy_assets/webassets/filter/libsass.py
weppy_assets/webassets/filter/node_sass.py
weppy_assets/webassets/filter/pyscss.py
weppy_assets/webassets/filter/requirejs.py
weppy_assets/webassets/filter/sass.py
weppy_assets/webassets/filter/slimit.py
weppy_assets/webassets/filter/slimmer.py
weppy_assets/webassets/filter/spritemapper.py
weppy_assets/webassets/filter/stylus.py
weppy_assets/webassets/filter/typescript.py
weppy_assets/webassets/filter/uglifyjs.py
weppy_assets/webassets/filter/yui.py
